Metadata-Version: 1.0
Name: dada-stor
Version: 0.0.9
Summary: Storage utilities used throughout dada-lake
Home-page: http://globally.ltd
Author: gltd
Author-email: hey@gltd.email
License: UNKNOWN
Platform: UNKNOWN
